{
    "trailers_beluga": [
        {
            "name": "beluga_trailer_1"
        },
        {
            "name": "beluga_trailer_2"
        }
    ],
    "trailers_factory": [
        {
            "name": "factory_trailer_1"
        },
        {
            "name": "factory_trailer_2"
        }
    ],
    "hangars": [
        "hangar1",
        "hangar2"
    ],
    "jig_types": {
        "typeA": {
            "name": "typeA",
            "size_empty": 4,
            "size_loaded": 4
        },
        "typeB": {
            "name": "typeB",
            "size_empty": 8,
            "size_loaded": 11
        },
        "typeC": {
            "name": "typeC",
            "size_empty": 9,
            "size_loaded": 18
        },
        "typeD": {
            "name": "typeD",
            "size_empty": 18,
            "size_loaded": 25
        },
        "typeE": {
            "name": "typeE",
            "size_empty": 32,
            "size_loaded": 32
        }
    },
    "racks": [
        {
            "name": "rack00",
            "size": 37,
            "jigs": [
                "jig0006",
                "jig0005",
                "jig0004",
                "jig0003",
                "jig0002"
            ]
        },
        {
            "name": "rack01",
            "size": 20,
            "jigs": [
                "jig0008",
                "jig0007",
                "jig0001",
                "jig0009"
            ]
        }
    ],
    "jigs": {
        "jig0001": {
            "name": "jig0001",
            "type": "typeA",
            "empty": false
        },
        "jig0002": {
            "name": "jig0002",
            "type": "typeB",
            "empty": false
        },
        "jig0003": {
            "name": "jig0003",
            "type": "typeA",
            "empty": true
        },
        "jig0004": {
            "name": "jig0004",
            "type": "typeB",
            "empty": true
        },
        "jig0005": {
            "name": "jig0005",
            "type": "typeA",
            "empty": true
        },
        "jig0006": {
            "name": "jig0006",
            "type": "typeB",
            "empty": true
        },
        "jig0007": {
            "name": "jig0007",
            "type": "typeB",
            "empty": true
        },
        "jig0008": {
            "name": "jig0008",
            "type": "typeA",
            "empty": true
        },
        "jig0009": {
            "name": "jig0009",
            "type": "typeA",
            "empty": false
        },
        "jig0010": {
            "name": "jig0010",
            "type": "typeA",
            "empty": false
        },
        "jig0011": {
            "name": "jig0011",
            "type": "typeA",
            "empty": false
        },
        "jig0012": {
            "name": "jig0012",
            "type": "typeA",
            "empty": false
        }
    },
    "production_lines": [
        {
            "name": "pl0",
            "schedule": [
                "jig0001"
            ]
        },
        {
            "name": "pl1",
            "schedule": [
                "jig0002"
            ]
        },
        {
            "name": "pl2",
            "schedule": [
                "jig0009"
            ]
        }
    ],
    "flights": [
        {
            "name": "beluga1",
            "incoming": [],
            "outgoing": [
                "typeA",
                "typeA",
                "typeA"
            ],
            "scheduled_arrival": 7.07
        },
        {
            "name": "beluga2",
            "incoming": [
                "jig0010",
                "jig0011",
                "jig0012"
            ],
            "outgoing": [
                "typeB",
                "typeB",
                "typeB"
            ],
            "scheduled_arrival": 7.86
        }
    ]
}